{
  "docs": {
    "Introduction": [
      "welcome"
    ],
    "Network": [
      "network/start",
      "network/balances",
      "network/deposits",
      "network/transfers",
      "network/fee-relay",
      "network/standard-exits",
      "network/in-flight-exits",
      "network/process-exits",
      "network/utxos",
      "network/challenge-exits"
    ],
    "Use Cases": [
      "use-cases/community-points",
      "use-cases/exchange"
    ],
    "Wallet": [
      "wallet/quick-start-webwallet"
    ],
    "Contracts": [
      "contracts/plasma-proposition",
      "contracts/admin-accounts",
      "contracts/morevp"
    ],
    "Watcher": [
      "watcher/run-watcher",
      "watcher/manage-vps",
      "watcher/manage-watcher"
    ],
    "Security": [
      "security/bug-bounty",
      "security/audits"
    ],
    "3-rd Party": [
      "3rd-party/metamask",
      "3rd-party/multibaas"
    ],
    "Concepts": [
      "network/blockchain-design",
      "network/byzantine-conditions",
      "network/network-architecture",
      "network/challenge-period",
      "network/exitbonds",
      "network/fees"
    ],
    "Resources": [
      "glossary",
      "faq",
      "api",
      "environments",
      "release-notes"
    ],
    "Migration Guides": [
      "migration-0.2-0.3",
      "migration-0.3-0.4"
    ]
  }
}